{
  "function": {
    "name": "GTAC_Model_IDUPdater",
    "namespace": "TcHmi.Functions.ICxx",
    "displayName": "GTAC_Model_IDUPdater",
    "description": "",
    "waitMode": "Synchronous",
    "category": "",
    "returnValue": {
      "type": "tchmi:general#/definitions/String"
    },
    "visible": true,
    "injectContextObject": false,
    "arguments": [
      {
        "name": "FixID",
        "displayName": "FixID",
        "type": "tchmi:general#/definitions/String",
        "description": "This is an important Parameter which does... This text is used in a tooltip.",
        "defaultValue": "",
        "required": true,
        "bindable": true,
        "restParameter": false,
        "asReference": false,
        "allowControlAttributeBindingOptions": false
      },
      {
        "name": "ModelID",
        "displayName": "ModelID",
        "type": "tchmi:general#/definitions/Number",
        "description": "",
        "defaultValue": "",
        "required": true,
        "bindable": true,
        "restParameter": false,
        "asReference": false,
        "allowControlAttributeBindingOptions": false
      }
    ]
  },
  "$schema": "./../../Packages/Beckhoff.TwinCAT.HMI.Framework.12.756.1/runtimes/native1.12-tchmi/Schema/FunctionDescription.Schema.json",
  "apiVersion": 1,
  "version": {
    "full": "0.0.0.0",
    "major": 0,
    "minor": 0,
    "revision": 0,
    "build": 0
  },
  "dependencyFiles": [
    {
      "name": "GTAC_Model_IDUPdater.js",
      "type": "JavaScript",
      "description": ""
    }
  ]
}