{
  "parameters": [
    {
      "name": "data-tchmi-srxx",
      "displayName": "SRxx",
      "allowSymbolExpressionsInObject": false,
      "visible": true,
      "type": "tchmi:server#/definitions/PLC1.udt_SRxx_ToUI_20260122",
      "category": "",
      "description": "",
      "requiredOnCompile": false,
      "readOnly": false,
      "bindable": true,
      "heritable": true,
      "propertyName": "SRxx",
      "propertySetterName": "setSRxx",
      "propertyGetterName": "getSRxx",
      "refTo": ""
    },
    {
      "name": "data-tchmi-srxx_discrete_in",
      "displayName": "SRxx_Discrete_In",
      "allowSymbolExpressionsInObject": false,
      "visible": true,
      "type": "tchmi:server#/definitions/PLC1.udt_SRxx_Input_Image",
      "category": "",
      "description": "",
      "requiredOnCompile": false,
      "readOnly": false,
      "bindable": true,
      "heritable": true,
      "propertyName": "SRxx_Discrete_In",
      "propertySetterName": "setSRxx_Discrete_In",
      "propertyGetterName": "getSRxx_Discrete_In",
      "refTo": ""
    }
  ],
  "virtualRights": [],
  "$schema": "./../../../Packages/Beckhoff.TwinCAT.HMI.Framework.12.762.53/runtimes/native1.12-tchmi/Schema/UserControlConfig.Schema.json",
  "description": ""
}